FlowCal/__init__.py
FlowCal/excel_ui.py
FlowCal/gate.py
FlowCal/io.py
FlowCal/mef.py
FlowCal/plot.py
FlowCal/stats.py
FlowCal/transform.py
FlowCal-1.1.0.dist-info/DESCRIPTION.rst
FlowCal-1.1.0.dist-info/METADATA
FlowCal-1.1.0.dist-info/RECORD
FlowCal-1.1.0.dist-info/WHEEL
FlowCal-1.1.0.dist-info/metadata.json
FlowCal-1.1.0.dist-info/pbr.json
FlowCal-1.1.0.dist-info/top_level.txt
