Metadata-Version: 2.0
Name: FlowCal
Version: 1.1.0
Summary: Flow Cytometry Calibration Library
Home-page: https://github.com/taborlab/FlowCal
Author: Sebastian Castillo-Hair
Author-email: castillohair@gmail.com
License: MIT
Keywords: flow cytometry
Platform: UNKNOWN
Classifier: Development Status :: 5 - Production/Stable
Classifier: Intended Audience :: Science/Research
Classifier: Topic :: Scientific/Engineering :: Bio-Informatics
Classifier: License :: OSI Approved :: MIT License
Classifier: Programming Language :: Python :: 2.7
Requires-Dist: XlsxWriter (>=0.5.2)
Requires-Dist: matplotlib (>=1.3.1)
Requires-Dist: numpy (>=1.8.2)
Requires-Dist: palettable (>=2.1.1)
Requires-Dist: pandas (>=0.16.1)
Requires-Dist: scikit-learn (>=0.16.0)
Requires-Dist: scipy (>=0.14.0)
Requires-Dist: xlrd (>=0.9.2)
